.gitignore
CHANGELOG.md
CONTRIBUTING.md
LICENSE.txt
Makefile
README.md
RELEASE.md
environment.yml
pyproject.toml
requirements-package.txt
requirements.txt
setup.cfg
setup.py
.github/workflows/test.yml
examples/sklearn_elasticnet_wine/MLproject
examples/sklearn_elasticnet_wine/conda-complex.yaml
examples/sklearn_elasticnet_wine/train.py
mlflow_algorithmia/__init__.py
mlflow_algorithmia/_generated_version.py
mlflow_algorithmia/conda_env.py
mlflow_algorithmia/deployment.py
mlflow_algorithmia.egg-info/PKG-INFO
mlflow_algorithmia.egg-info/SOURCES.txt
mlflow_algorithmia.egg-info/dependency_links.txt
mlflow_algorithmia.egg-info/entry_points.txt
mlflow_algorithmia.egg-info/not-zip-safe
mlflow_algorithmia.egg-info/requires.txt
mlflow_algorithmia.egg-info/top_level.txt
mlflow_algorithmia/templates/algorithmia_utils.py
mlflow_algorithmia/templates/entrypoint.py
mlflow_algorithmia/templates/gitignore_all
mlflow_algorithmia/templates/gitignore_repo
mlflow_algorithmia/templates/mlflow_wrapper.py
mlflow_algorithmia/templates/requirements.txt
mlflow_algorithmia/tests/__init__.py
mlflow_algorithmia/tests/test_conda_yaml.py
mlflow_algorithmia/tests/test_import.py
mlflow_algorithmia/tests/test_settings.py