Metadata-Version: 2.1
Name: mlflow-algorithmia
Version: 0.1.3
Summary: UNKNOWN
Home-page: https://github.com/algorithmia/mlflow-algorithmia
Maintainer: Algorithmia
Maintainer-email: drodriguez@algorithmia.io
License: Apache License, Version 2.0
Platform: UNKNOWN
Classifier: License :: OSI Approved :: Apache Software License
Classifier: Programming Language :: Python :: 3.6
Classifier: Programming Language :: Python :: 3.7
Classifier: Programming Language :: Python :: 3.8
Requires-Python: >=3.6
Provides-Extra: test
Provides-Extra: dev
